aoaomail/__init__.py
aoaomail/helper.py
mailhelper/__init__.py
mailhelper/helper.py
mailsdk/__init__.py
mailsdk/help.py
aoaomail-0.0.6.dist-info/METADATA
aoaomail-0.0.6.dist-info/WHEEL
aoaomail-0.0.6.dist-info/top_level.txt
aoaomail-0.0.6.dist-info/RECORD
