Metadata-Version: 2.1
Name: aoaomail
Version: 0.0.6
Summary: easy python email
Home-page: http://www.czaoao.me
Author: czaoao
Author-email: 717842816@qq.com
License: MIT license
Platform: any
